nbkits/__init__.py
nbkits/display.py
nbkits/utils.py
nbkits/xlstyler.py
nbkits-0.2.5.dist-info/LICENSE
nbkits-0.2.5.dist-info/METADATA
nbkits-0.2.5.dist-info/WHEEL
nbkits-0.2.5.dist-info/top_level.txt
nbkits-0.2.5.dist-info/RECORD
