Metadata-Version: 2.1
Name: nbkits
Version: 0.2.5
Summary: A toolkit for jupyter's notebook
Author-email: "Lyu, Chenggong" <lcgong@gmail.com>
Project-URL: Homepage, https://github.com/lcgong/nbkits
Project-URL: Bug Tracker, https://github.com/lcgong/nbkits/issues
Classifier: Programming Language :: Python :: 3
Classifier: License :: OSI Approved :: MIT License
Classifier: Operating System :: OS Independent
Requires-Python: >=3.8
License-File: LICENSE
Requires-Dist: matplotlib >=3.8
Requires-Dist: ipython >=8.0
Requires-Dist: openpyxl >=3.1
Provides-Extra: dev
Requires-Dist: pytest ; extra == 'dev'
Requires-Dist: tox ; extra == 'dev'
